[{"bodyLinks":"","FeedId":"a1814076-7e07-4aea-8653-3d7ab82d7675","category":"sports_baseball","title":"How to Play Baseball : How to Hit a Baseball","author":"expertvillage","shortDescription":"How to Play Baseball : How to Hit a Baseball","description":"How to Play Baseball : How to Hit a Baseball","link":"","linkType":"channel_youtube","linkValue":"hyHKyCI4oZE","image":"http://img.youtube.com/vi/hyHKyCI4oZE/default.jpg","publishedDate":"\/Date(1474906740890)\/","rank":100,"beginDate":"\/Date(1474906740890)\/","endDate":"\/Date(1474906740890)\/","totalRows":0,"warnings":"","sideeffects":"","dosage":"","anticoagulant":false,"carcinogenic":false,"hypoglycemic":false,"liverdamage":false,"kidneydamage":false,"city":"","state":"","postalCode":"","country":"","areaCode":"","closed":false,"carousel":false,"carousel_caption":"","showvideo":false,"moviecategory":"SciFi","duration":"00:00:00"},{"bodyLinks":"","FeedId":"14dbf48a-330e-4097-bbf9-43bb585a1042","category":"sports_baseball","title":"Some of the greatest baseball plays you will ever see","author":"Baseball \u0026 Softball around the World","shortDescription":"Some of the greatest baseball plays you will ever see","description":"Some of the greatest baseball plays you will ever see","link":"","linkType":"embed_youtube","linkValue":"ROXqddQYBH4","image":"http://img.youtube.com/vi/ROXqddQYBH4/default.jpg","publishedDate":"\/Date(1474906711280)\/","rank":100,"beginDate":"\/Date(1474906711280)\/","endDate":"\/Date(1474906711280)\/","totalRows":0,"warnings":"","sideeffects":"","dosage":"","anticoagulant":false,"carcinogenic":false,"hypoglycemic":false,"liverdamage":false,"kidneydamage":false,"city":"","state":"","postalCode":"","country":"","areaCode":"","closed":false,"carousel":false,"carousel_caption":"","showvideo":false,"moviecategory":"SciFi","duration":"00:00:00"},{"bodyLinks":"","FeedId":"9fcecd76-bbb5-49d7-b813-f0c99c62bb3c","category":"sports_baseball","title":"How to Hit a Home Run with Domingo Ayala","author":"Domingo Ayala","shortDescription":"How to Hit a Home Run with Domingo Ayala","description":"How to Hit a Home Run with Domingo Ayala","link":"","linkType":"channel_youtube","linkValue":"neHgPKWY4Qg","image":"http://img.youtube.com/vi/neHgPKWY4Qg/default.jpg","publishedDate":"\/Date(1474906619257)\/","rank":100,"beginDate":"\/Date(1474906619257)\/","endDate":"\/Date(1474906619257)\/","totalRows":0,"warnings":"","sideeffects":"","dosage":"","anticoagulant":false,"carcinogenic":false,"hypoglycemic":false,"liverdamage":false,"kidneydamage":false,"city":"","state":"","postalCode":"","country":"","areaCode":"","closed":false,"carousel":false,"carousel_caption":"","showvideo":false,"moviecategory":"SciFi","duration":"00:00:00"},{"bodyLinks":"","FeedId":"62f8cd19-a08d-45ec-bd42-70c83a4cf965","category":"sports_baseball","title":"How to Play Baseball Like Tim Tebow","author":"Domingo Ayala","shortDescription":"How to Play Baseball Like Tim Tebow","description":"How to Play Baseball Like Tim Tebow","link":"","linkType":"channel_youtube","linkValue":"uVAL-cGCOfY","image":"http://img.youtube.com/vi/uVAL-cGCOfY/default.jpg","publishedDate":"\/Date(1474906584733)\/","rank":100,"beginDate":"\/Date(1474906584733)\/","endDate":"\/Date(1474906584733)\/","totalRows":0,"warnings":"","sideeffects":"","dosage":"","anticoagulant":false,"carcinogenic":false,"hypoglycemic":false,"liverdamage":false,"kidneydamage":false,"city":"","state":"","postalCode":"","country":"","areaCode":"","closed":false,"carousel":false,"carousel_caption":"","showvideo":false,"moviecategory":"SciFi","duration":"00:00:00"},{"bodyLinks":"","FeedId":"817ba38c-68d3-403f-bb8a-72e69c41bf4f","category":"sports_baseball","title":"Baseball Rules of Engagement","author":"TruScribeVideos","shortDescription":"Baseball Rules of Engagement","description":"Baseball Rules of Engagement","link":"","linkType":"embed_youtube","linkValue":"0bKkGeROiPA","image":"http://img.youtube.com/vi/0bKkGeROiPA/default.jpg","publishedDate":"\/Date(1474906551897)\/","rank":100,"beginDate":"\/Date(1474906551897)\/","endDate":"\/Date(1474906551897)\/","totalRows":0,"warnings":"","sideeffects":"","dosage":"","anticoagulant":false,"carcinogenic":false,"hypoglycemic":false,"liverdamage":false,"kidneydamage":false,"city":"","state":"","postalCode":"","country":"","areaCode":"","closed":false,"carousel":false,"carousel_caption":"","showvideo":false,"moviecategory":"SciFi","duration":"00:00:00"},{"bodyLinks":"","FeedId":"e2537462-4a19-4cbc-baf1-634a065ae2e7","category":"sports_baseball","title":"Baseball Tips \u0026 Tricks : How to Play Baseball","author":"expertvillage","shortDescription":"Baseball Tips \u0026 Tricks : How to Play Baseball","description":"Baseball Tips \u0026 Tricks : How to Play Baseball","link":"","linkType":"channel_youtube","linkValue":"Wxd_UT84qb0","image":"http://img.youtube.com/vi/Wxd_UT84qb0/default.jpg","publishedDate":"\/Date(1474906514020)\/","rank":100,"beginDate":"\/Date(1474906514020)\/","endDate":"\/Date(1474906514020)\/","totalRows":0,"warnings":"","sideeffects":"","dosage":"","anticoagulant":false,"carcinogenic":false,"hypoglycemic":false,"liverdamage":false,"kidneydamage":false,"city":"","state":"","postalCode":"","country":"","areaCode":"","closed":false,"carousel":false,"carousel_caption":"","showvideo":false,"moviecategory":"SciFi","duration":"00:00:00"},{"bodyLinks":"","FeedId":"4222baaf-3329-4358-ad93-0749a254d878","category":"sports_baseball","title":"Greatest Plays in Baseball 2016 - Part I of May","author":"Baseball \u0026 Softball around the World","shortDescription":"Greatest Plays in Baseball 2016 - Part I of May","description":"Greatest Plays in Baseball 2016 - Part I of May","link":"","linkType":"channel_youtube","linkValue":"PmBGBr8P8-8","image":"http://img.youtube.com/vi/PmBGBr8P8-8/default.jpg","publishedDate":"\/Date(1474784188323)\/","rank":100,"beginDate":"\/Date(1474784188323)\/","endDate":"\/Date(1474784188323)\/","totalRows":0,"warnings":"","sideeffects":"","dosage":"","anticoagulant":false,"carcinogenic":false,"hypoglycemic":false,"liverdamage":false,"kidneydamage":false,"city":"","state":"","postalCode":"","country":"","areaCode":"","closed":false,"carousel":false,"carousel_caption":"","showvideo":false,"moviecategory":"SciFi","duration":"00:00:00"}]